ethereum_scan/__init__.py
ethereum_scan/features/__init__.py
ethereum_scan/features/obj.py
ethereum_scan/tool/Exceptions.py
ethereum_scan/tool/Tool.py
ethereum_scan/tool/__init__.py
ethereum_scan-1.0.0.5.dist-info/LICENSE
ethereum_scan-1.0.0.5.dist-info/METADATA
ethereum_scan-1.0.0.5.dist-info/WHEEL
ethereum_scan-1.0.0.5.dist-info/top_level.txt
ethereum_scan-1.0.0.5.dist-info/RECORD
