Metadata-Version: 2.1
Name: ethereum-scan
Version: 1.0.0.5
Summary: The Ethereum scanning tool constructed with Python, based on the open API provided by EtherScan, ensures the accuracy of the data
Author-email: French <french@hoime.cn>
License: Mozilla Public License Version 2.0
Project-URL: Homepage, https://github.com/french-home/ethereum-scan
Project-URL: Bug Tracker, https://github.com/french-home/ethereum-scan/issues
Classifier: Programming Language :: Python :: 3
Classifier: License :: OSI Approved :: Mozilla Public License 2.0 (MPL 2.0)
Classifier: Operating System :: OS Independent
Requires-Python: >=3
License-File: LICENSE
